RESTModels/__init__.py
RESTModels/builders.py
RESTModels/clients.py
RESTModels/requests.py
RESTModels/resources.py
RESTModels/parsers/__init__.py
RESTModels/parsers/args_parsers.py
RESTModels/parsers/response_parsers.py
RESTModels/parsers/type_alias_parsers.py
RESTModels-1.1.1.dist-info/METADATA
RESTModels-1.1.1.dist-info/WHEEL
RESTModels-1.1.1.dist-info/top_level.txt
RESTModels-1.1.1.dist-info/RECORD
