Metadata-Version: 2.1
Name: RESTModels
Version: 1.1.1
Summary: API client by resource models for RESTful API over JSON
Author-email: Sequew <kryseyt@gmail.com>
Project-URL: Homepage, https://github.com/KrySeyt/RESTModels
Requires-Dist: requests
